pigeon/__init__.py
pigeon/test.py
pigeon/url/__init__.py
pigeon/url/utils.py
django_pigeon-0.4.0.dist-info/LICENSE
django_pigeon-0.4.0.dist-info/WHEEL
django_pigeon-0.4.0.dist-info/METADATA
django_pigeon-0.4.0.dist-info/RECORD
