Metadata-Version: 2.1
Name: django-pigeon
Version: 0.4.0
Summary: Test utilities for Django projects.
Home-page: https://github.com/RevolutionTech/django-pigeon
License: ISC
Author: Lucas Connors
Author-email: lucas@revolutiontech.ca
Requires-Python: >=3.6.1,<4.0.0
Classifier: Environment :: Web Environment
Classifier: Framework :: Django
Classifier: Framework :: Django :: 2.2
Classifier: Framework :: Django :: 3.0
Classifier: Framework :: Django :: 3.1
Classifier: Intended Audience :: Developers
Classifier: License :: OSI Approved
Classifier: Operating System :: OS Independent
Classifier: Programming Language :: Python :: 3
Classifier: Programming Language :: Python :: 3.7
Classifier: Programming Language :: Python :: 3.8
Classifier: Programming Language :: Python :: 3.9
Classifier: Topic :: Software Development :: Testing
Classifier: Topic :: Utilities
Requires-Dist: Django (>=2.2)
Project-URL: Repository, https://github.com/RevolutionTech/django-pigeon
